autoelbow_rupakbob/__init__.py
autoelbow_rupakbob/autoelbow.py
autoelbow-0.0.4.dist-info/LICENSE
autoelbow-0.0.4.dist-info/METADATA
autoelbow-0.0.4.dist-info/WHEEL
autoelbow-0.0.4.dist-info/top_level.txt
autoelbow-0.0.4.dist-info/RECORD
